mips.v
module mips32(clk1,clk2);
  input clk1,clk2;
  reg [31:0] PC,IF_ID_NPC,IF_ID_IR;
  reg [31:0] ID_EX_NPC,ID_EX_IR,ID_EX_A,ID_EX_B,ID_EX_IMM;
  reg [2:0] ID_EX_TYPE,EX_MEM_TYPE,MEM_WB_TYPE;
  reg [31:0] EX_MEM_IR,EX_MEM_ALUOUT,EX_MEM_B;
  reg EX_MEM_COND;
  reg [31:0] MEM_WB_LMD,MEM_WB_ALUOUT,MEM_WB_IR;
  
  reg [31:0] REG[31:0];
  reg [31:0] MEM[1023:0];
  
  parameter ADD=6'b000000, SUB=6'b000001, AND=6'b000010, OR=6'b000011,  SLT=6'b000100, MUL=6'b000101, HLT=6'b111111, LW=6'b001000, SW=6'b001001,ADDI=6'b001010, SUBI=6'b001011, SLTI=6'b001100, BNEQZ=6'b001101,BEQZ=6'b001110;
  
  parameter RR_ALU=3'b000, RM_ALU=3'b001, LOAD=3'b010, STORE=3'b011, BRANCH=3'b100, HALT=3'b101;
  reg HALTED;
  reg TAKEN_BRANCH;
  
  //IF
  always @(posedge clk1)
    begin
 	 if(HALTED == 0)
   	 begin
      if (((EX_MEM_IR[31:26] == BNEQZ) && (EX_MEM_COND == 0)) || ((EX_MEM_IR[31:26] == BEQZ) && (EX_MEM_COND == 1)))
        begin
          IF_ID_IR <= #2 MEM[EX_MEM_ALUOUT];
          TAKEN_BRANCH <= #2 1'b1;
          IF_ID_NPC <= #2 EX_MEM_ALUOUT + 1;
          PC <= #2 EX_MEM_ALUOUT + 1;
        end
      else
        begin
          IF_ID_IR <= #2 MEM[PC];
          IF_ID_NPC <= #2 PC + 1;
          PC <= #2 PC + 1;
        end
    end
    end
  
  //ID
  always @(posedge clk2)
    begin
  	if(HALTED == 0)
    	begin
     	    ID_EX_NPC <= #2 IF_ID_NPC;
      	  ID_EX_IR <= #2 IF_ID_IR;
          ID_EX_IMM <= #2 {{16{IF_ID_IR[15]}},{IF_ID_IR[15:0]}}; 
          
          if(IF_ID_IR[25:21] == 5'b00000) ID_EX_A <= 0;
          else ID_EX_A <= #2 REG[IF_ID_IR[25:21]];			//RS
          
          if(IF_ID_IR[20:16] == 5'b00000) ID_EX_B <= 0;
          else ID_EX_B <= #2 REG[IF_ID_IR[20:16]];			//RT
    	
      
      case(IF_ID_IR[31:26])
        ADD, SUB, AND, OR, SLT, MUL: ID_EX_TYPE <= #2 RR_ALU;
        ADDI, SUBI, SLTI           : ID_EX_TYPE <= #2 RM_ALU;
        LW                         : ID_EX_TYPE <= #2 LOAD;
        SW                         : ID_EX_TYPE <= #2 STORE;
        BNEQZ, BEQZ                : ID_EX_TYPE <= #2 BRANCH;
        HLT                        : ID_EX_TYPE <= #2 HALT;
        default                    : ID_EX_TYPE <= #2 HALT;   
      endcase
      end
        
    end
  
  //EX
  always @( posedge clk1)
    begin
    if(HALTED==0)
      begin
      TAKEN_BRANCH <= #2 1'b0;
      EX_MEM_IR <= #2 ID_EX_IR;
      EX_MEM_TYPE <= #2 ID_EX_TYPE;
      
      case(ID_EX_TYPE)
        RR_ALU : begin
          case(ID_EX_IR[31:26])
            ADD : EX_MEM_ALUOUT <= #2 ID_EX_A + ID_EX_B;
            SUB : EX_MEM_ALUOUT <= #2 ID_EX_A - ID_EX_B;
            AND : EX_MEM_ALUOUT <= #2 ID_EX_A & ID_EX_B;
            OR  : EX_MEM_ALUOUT <= #2 ID_EX_A | ID_EX_B;
            SLT : EX_MEM_ALUOUT <= #2 ID_EX_A < ID_EX_B;
            MUL : EX_MEM_ALUOUT <= #2 ID_EX_A * ID_EX_B;
            default : EX_MEM_ALUOUT <= #2 32'bxxxxxxxx;
          endcase
        end
        
        RM_ALU : begin
          case(ID_EX_IR[31:26])
            ADDI : EX_MEM_ALUOUT <= #2 ID_EX_A + ID_EX_IMM;
            SUBI : EX_MEM_ALUOUT <= #2 ID_EX_A - ID_EX_IMM;
            SLTI : EX_MEM_ALUOUT <= #2 ID_EX_A < ID_EX_IMM;
            default : EX_MEM_ALUOUT <= #2 32'bxxxxxxxx;
          endcase
        end
        
        LOAD, STORE : begin
          EX_MEM_ALUOUT <= #2 ID_EX_A + ID_EX_IMM;
          EX_MEM_B <= #2 ID_EX_B;
        end
        
        BRANCH : begin
          EX_MEM_ALUOUT <= #2 ID_EX_NPC + ID_EX_IMM;
          EX_MEM_COND <= #2 (ID_EX_A==0);
        end
        
      endcase
      end
    end
  
        
  
  //MEM
  
  always @(posedge clk2)
    if (HALTED == 0)
    begin
      MEM_WB_IR <= EX_MEM_IR;
      MEM_WB_TYPE <= EX_MEM_TYPE;
      
      case(EX_MEM_TYPE)
        RR_ALU, RM_ALU : MEM_WB_ALUOUT <= #2 EX_MEM_ALUOUT;
        
        LOAD : MEM_WB_LMD <= #2 MEM[EX_MEM_ALUOUT];
        
        STORE : if (TAKEN_BRANCH == 0) MEM[EX_MEM_ALUOUT] <= #2 EX_MEM_B;
      endcase
    end
   
  
  
  //WB
  
  always @(posedge clk1)
    begin
      if(TAKEN_BRANCH == 0)
        case(MEM_WB_TYPE) 
          RR_ALU : REG[MEM_WB_IR[15:11]] <= #2 MEM_WB_ALUOUT;
          
          RM_ALU : REG[MEM_WB_IR[20:16]] <= #2 MEM_WB_ALUOUT;
          
          LOAD : REG[MEM_WB_IR[20:16]] <= #2 MEM_WB_LMD;
          
          HALT : HALTED <= #2 1'b1;
        endcase
    end
  
endmodule

mips_tb2.v
`include "mips.v"

module mips_tb2;

    reg clk1, clk2;
    integer k;

    mips32 mips(clk1, clk2);

    initial begin
        clk1=0; clk2=0;
        repeat(20) 
        begin 
            #5 clk1=1; #5 clk1=0;
            #5 clk2=1; #5 clk2=0;
        end
    end

    initial begin
      for(k=0; k<=31; k++) begin
        mips.REG[k] = k;
      end

      mips.MEM[0] = 32'h28010078;   // ADDI R1, R0, 120

      mips.MEM[1] = 32'h0c631800;   // dummy

      mips.MEM[2] = 32'h20220000;   // LW R2, 0(R1)

      mips.MEM[3] = 32'h0c631800;   // dummy

      mips.MEM[4] = 32'h2842002d;   // ADDI R2, R2, 45

      mips.MEM[5] = 32'h0c631800;   // dummy

      mips.MEM[6] = 32'h24220001;   // SW R2, 1(R1)

      mips.MEM[7] = 32'hfc000000;  // HLT  

      mips.MEM[120] = 85;

      mips.HALTED = 0;
      mips.TAKEN_BRANCH = 0;
      mips.PC = 0;

      #500;
        $display("Mem[120]: %0d \nMem[121] : %0d", mips.MEM[120], mips.MEM[121]);
    end


    initial begin
      $dumpfile("mips2.vcd");
      $dumpvars(0, mips_tb2);
      #600 $finish;
    end



endmodule

// 0: ADDI R1, R0, 120      → R1 = 120
// 1: OR   R3, R3, R3       → dummy
// 2: LW   R2, 0(R1)        → R2 = MEM[120] = 85
// 3: OR   R3, R3, R3       → dummy
// 4: ADDI R2, R2, 45       → R2 = 85 + 45 = 130
// 5: OR   R3, R3, R3       → dummy
// 6: SW   R2, 1(R1)        → MEM[121] = 130  
// 7: HLT

outputs/mips2.vcd
$date
	Mon Jun 08 22:38:13 2026
$end
$version
	Icarus Verilog
$end
$timescale
	1s
$end
$scope module mips_tb2 $end
$var reg 1 ! clk1 $end
$var reg 1 " clk2 $end
$var integer 32 # k [31:0] $end
$scope module mips $end
$var wire 1 ! clk1 $end
$var wire 1 " clk2 $end
$var parameter 6 $ ADD $end
$var parameter 6 % ADDI $end
$var parameter 6 & AND $end
$var parameter 6 ' BEQZ $end
$var parameter 6 ( BNEQZ $end
$var parameter 3 ) BRANCH $end
$var parameter 3 * HALT $end
$var parameter 6 + HLT $end
$var parameter 3 , LOAD $end
$var parameter 6 - LW $end
$var parameter 6 . MUL $end
$var parameter 6 / OR $end
$var parameter 3 0 RM_ALU $end
$var parameter 3 1 RR_ALU $end
$var parameter 6 2 SLT $end
$var parameter 6 3 SLTI $end
$var parameter 3 4 STORE $end
$var parameter 6 5 SUB $end
$var parameter 6 6 SUBI $end
$var parameter 6 7 SW $end
$var reg 32 8 EX_MEM_ALUOUT [31:0] $end
$var reg 32 9 EX_MEM_B [31:0] $end
$var reg 1 : EX_MEM_COND $end
$var reg 32 ; EX_MEM_IR [31:0] $end
$var reg 3 < EX_MEM_TYPE [2:0] $end
$var reg 1 = HALTED $end
$var reg 32 > ID_EX_A [31:0] $end
$var reg 32 ? ID_EX_B [31:0] $end
$var reg 32 @ ID_EX_IMM [31:0] $end
$var reg 32 A ID_EX_IR [31:0] $end
$var reg 32 B ID_EX_NPC [31:0] $end
$var reg 3 C ID_EX_TYPE [2:0] $end
$var reg 32 D IF_ID_IR [31:0] $end
$var reg 32 E IF_ID_NPC [31:0] $end
$var reg 32 F MEM_WB_ALUOUT [31:0] $end
$var reg 32 G MEM_WB_IR [31:0] $end
$var reg 32 H MEM_WB_LMD [31:0] $end
$var reg 3 I MEM_WB_TYPE [2:0] $end
$var reg 32 J PC [31:0] $end
$var reg 1 K TAKEN_BRANCH $end
$upscope $end
$upscope $end
$enddefinitions $end
$comment Show the parameter values. $end
$dumpall
b1001 7
b1011 6
b1 5
b11 4
b1100 3
b100 2
b0 1
b1 0
b11 /
b101 .
b1000 -
b10 ,
b111111 +
b101 *
b100 )
b1101 (
b1110 '
b10 &
b1010 %
b0 $
$end
#0
$dumpvars
0K
b0 J
bx I
bx H
bx G
bx F
bx E
bx D
bx C
bx B
bx A
bx @
bx ?
bx >
0=
bx <
bx ;
x:
bx 9
bx 8
b100000 #
0"
0!
$end
#5
1!
#7
b1 J
b1 E
b101000000000010000000001111000 D
#10
0!
#15
b0 >
1"
#17
b1 C
b1 ?
b1111000 @
b101000000000010000000001111000 A
b1 B
#20
0"
#25
1!
#27
b1111000 8
b1 <
b101000000000010000000001111000 ;
b10 J
b10 E
b1100011000110001100000000000 D
#30
0!
#35
b1 I
b101000000000010000000001111000 G
1"
#37
b1111000 F
b0 C
b11 ?
b11 >
b1100000000000 @
b1100011000110001100000000000 A
b10 B
#40
0"
#45
1!
#47
b11 J
b11 E
b100000001000100000000000000000 D
b11 8
b0 <
b1100011000110001100000000000 ;
#50
0!
#55
b0 I
b1100011000110001100000000000 G
1"
#57
b10 C
b10 ?
b1111000 >
b0 @
b100000001000100000000000000000 A
b11 B
b11 F
#60
0"
#65
1!
#67
b10 9
b1111000 8
b10 <
b100000001000100000000000000000 ;
b100 J
b100 E
b1100011000110001100000000000 D
#70
0!
#75
b10 I
b100000001000100000000000000000 G
1"
#77
b1010101 H
b0 C
b11 ?
b11 >
b1100000000000 @
b1100011000110001100000000000 A
b100 B
#80
0"
#85
1!
#87
b101 J
b101 E
b101000010000100000000000101101 D
b11 8
b0 <
b1100011000110001100000000000 ;
#90
0!
#95
b0 I
b1100011000110001100000000000 G
1"
#97
b1 C
b1010101 ?
b1010101 >
b101101 @
b101000010000100000000000101101 A
b101 B
#100
0"
#105
1!
#107
b10000010 8
b1 <
b101000010000100000000000101101 ;
b110 J
b110 E
b1100011000110001100000000000 D
#110
0!
#115
b1 I
b101000010000100000000000101101 G
1"
#117
b10000010 F
b0 C
b11 ?
b11 >
b1100000000000 @
b1100011000110001100000000000 A
b110 B
#120
0"
#125
1!
#127
b111 J
b111 E
b100100001000100000000000000001 D
b11 8
b0 <
b1100011000110001100000000000 ;
#130
0!
#135
b0 I
b1100011000110001100000000000 G
1"
#137
b11 C
b10000010 ?
b1111000 >
b1 @
b100100001000100000000000000001 A
b111 B
b11 F
#140
0"
#145
1!
#147
b10000010 9
b1111001 8
b11 <
b100100001000100000000000000001 ;
b1000 J
b1000 E
b11111100000000000000000000000000 D
#150
0!
#155
b11 I
b100100001000100000000000000001 G
b0 ?
b0 >
1"
#157
b101 C
b0 @
b11111100000000000000000000000000 A
b1000 B
#160
0"
#165
1!
#167
b1001 J
b1001 E
bx D
b101 <
b11111100000000000000000000000000 ;
#170
0!
#175
b101 I
b11111100000000000000000000000000 G
1"
#177
bx ?
bx >
bx @
bx A
b1001 B
#180
0"
#185
1!
#187
1=
bx ;
b1010 J
b1010 E
