mips.v
module mips32(clk1,clk2);
  input clk1,clk2;
  reg [31:0] PC,IF_ID_NPC,IF_ID_IR;
  reg [31:0] ID_EX_NPC,ID_EX_IR,ID_EX_A,ID_EX_B,ID_EX_IMM;
  reg [2:0] ID_EX_TYPE,EX_MEM_TYPE,MEM_WB_TYPE;
  reg [31:0] EX_MEM_IR,EX_MEM_ALUOUT,EX_MEM_B;
  reg EX_MEM_COND;
  reg [31:0] MEM_WB_LMD,MEM_WB_ALUOUT,MEM_WB_IR;
  
  reg [31:0] REG[31:0];
  reg [31:0] MEM[1023:0];
  
  parameter ADD=6'b000000, SUB=6'b000001, AND=6'b000010, OR=6'b000011,  SLT=6'b000100, MUL=6'b000101, HLT=6'b111111, LW=6'b001000, SW=6'b001001,ADDI=6'b001010, SUBI=6'b001011, SLTI=6'b001100, BNEQZ=6'b001101,BEQZ=6'b001110;
  
  parameter RR_ALU=3'b000, RM_ALU=3'b001, LOAD=3'b010, STORE=3'b011, BRANCH=3'b100, HALT=3'b101;
  reg HALTED;
  reg TAKEN_BRANCH;
  
  //IF
  always @(posedge clk1)
    begin
 	 if(HALTED == 0)
   	 begin
      if (((EX_MEM_IR[31:26] == BNEQZ) && (EX_MEM_COND == 0)) || ((EX_MEM_IR[31:26] == BEQZ) && (EX_MEM_COND == 1)))
        begin
          IF_ID_IR <= #2 MEM[EX_MEM_ALUOUT];
          TAKEN_BRANCH <= #2 1'b1;
          IF_ID_NPC <= #2 EX_MEM_ALUOUT + 1;
          PC <= #2 EX_MEM_ALUOUT + 1;
        end
      else
        begin
          IF_ID_IR <= #2 MEM[PC];
          IF_ID_NPC <= #2 PC + 1;
          PC <= #2 PC + 1;
        end
    end
    end
  
  //ID
  always @(posedge clk2)
    begin
  	if(HALTED == 0)
    	begin
     	    ID_EX_NPC <= #2 IF_ID_NPC;
      	  ID_EX_IR <= #2 IF_ID_IR;
          ID_EX_IMM <= #2 {{16{IF_ID_IR[15]}},{IF_ID_IR[15:0]}}; 
          
          if(IF_ID_IR[25:21] == 5'b00000) ID_EX_A <= 0;
          else ID_EX_A <= #2 REG[IF_ID_IR[25:21]];			//RS
          
          if(IF_ID_IR[20:16] == 5'b00000) ID_EX_B <= 0;
          else ID_EX_B <= #2 REG[IF_ID_IR[20:16]];			//RT
    	
      
      case(IF_ID_IR[31:26])
        ADD, SUB, AND, OR, SLT, MUL: ID_EX_TYPE <= #2 RR_ALU;
        ADDI, SUBI, SLTI           : ID_EX_TYPE <= #2 RM_ALU;
        LW                         : ID_EX_TYPE <= #2 LOAD;
        SW                         : ID_EX_TYPE <= #2 STORE;
        BNEQZ, BEQZ                : ID_EX_TYPE <= #2 BRANCH;
        HLT                        : ID_EX_TYPE <= #2 HALT;
        default                    : ID_EX_TYPE <= #2 HALT;   
      endcase
      end
        
    end
  
  //EX
  always @( posedge clk1)
    begin
    if(HALTED==0)
      begin
      TAKEN_BRANCH <= #2 1'b0;
      EX_MEM_IR <= #2 ID_EX_IR;
      EX_MEM_TYPE <= #2 ID_EX_TYPE;
      
      case(ID_EX_TYPE)
        RR_ALU : begin
          case(ID_EX_IR[31:26])
            ADD : EX_MEM_ALUOUT <= #2 ID_EX_A + ID_EX_B;
            SUB : EX_MEM_ALUOUT <= #2 ID_EX_A - ID_EX_B;
            AND : EX_MEM_ALUOUT <= #2 ID_EX_A & ID_EX_B;
            OR  : EX_MEM_ALUOUT <= #2 ID_EX_A | ID_EX_B;
            SLT : EX_MEM_ALUOUT <= #2 ID_EX_A < ID_EX_B;
            MUL : EX_MEM_ALUOUT <= #2 ID_EX_A * ID_EX_B;
            default : EX_MEM_ALUOUT <= #2 32'bxxxxxxxx;
          endcase
        end
        
        RM_ALU : begin
          case(ID_EX_IR[31:26])
            ADDI : EX_MEM_ALUOUT <= #2 ID_EX_A + ID_EX_IMM;
            SUBI : EX_MEM_ALUOUT <= #2 ID_EX_A - ID_EX_IMM;
            SLTI : EX_MEM_ALUOUT <= #2 ID_EX_A < ID_EX_IMM;
            default : EX_MEM_ALUOUT <= #2 32'bxxxxxxxx;
          endcase
        end
        
        LOAD, STORE : begin
          EX_MEM_ALUOUT <= #2 ID_EX_A + ID_EX_IMM;
          EX_MEM_B <= #2 ID_EX_B;
        end
        
        BRANCH : begin
          EX_MEM_ALUOUT <= #2 ID_EX_NPC + ID_EX_IMM;
          EX_MEM_COND <= #2 (ID_EX_A==0);
        end
        
      endcase
      end
    end
  
        
  
  //MEM
  
  always @(posedge clk2)
    if (HALTED == 0)
    begin
      MEM_WB_IR <= EX_MEM_IR;
      MEM_WB_TYPE <= EX_MEM_TYPE;
      
      case(EX_MEM_TYPE)
        RR_ALU, RM_ALU : MEM_WB_ALUOUT <= #2 EX_MEM_ALUOUT;
        
        LOAD : MEM_WB_LMD <= #2 MEM[EX_MEM_ALUOUT];
        
        STORE : if (TAKEN_BRANCH == 0) MEM[EX_MEM_ALUOUT] <= #2 EX_MEM_B;
      endcase
    end
   
  
  
  //WB
  
  always @(posedge clk1)
    begin
      if(TAKEN_BRANCH == 0)
        case(MEM_WB_TYPE) 
          RR_ALU : REG[MEM_WB_IR[15:11]] <= #2 MEM_WB_ALUOUT;
          
          RM_ALU : REG[MEM_WB_IR[20:16]] <= #2 MEM_WB_ALUOUT;
          
          LOAD : REG[MEM_WB_IR[20:16]] <= #2 MEM_WB_LMD;
          
          HALT : HALTED <= #2 1'b1;
        endcase
    end
  
endmodule

mips_tb3.v
`include "mips.v"

module mips_tb3;

  reg clk1, clk2;
  integer k;

  mips32 mips(clk1, clk2);   

  initial begin
    clk1 = 0; clk2 = 0;
    repeat(50) begin
      #5 clk1 = 1; #5 clk1 = 0;
      #5 clk2 = 1; #5 clk2 = 0;
    end
  end

  initial begin

    for (k = 0; k < 31; k = k + 1)
      mips.REG[k] = k;

    mips.MEM[0]  = 32'h280a00c8;
    mips.MEM[1]  = 32'h28020001;
    mips.MEM[2]  = 32'h0e94a000;
    mips.MEM[3]  = 32'h21430000;
    mips.MEM[4]  = 32'h0e94a000;
    mips.MEM[5]  = 32'h14431000;
    mips.MEM[6]  = 32'h2c630001;
    mips.MEM[7]  = 32'h0e94a000;
    mips.MEM[8]  = 32'h3460fffc;
    mips.MEM[9]  = 32'h2542fffe;
    mips.MEM[10] = 32'hfc000000;

    mips.MEM[200] = 7;

    mips.HALTED = 0;
    mips.TAKEN_BRANCH = 0;
    mips.PC = 0;

    #6000;

    $display("Mem[200] = %0d, Mem[198] = %0d", mips.MEM[200], mips.MEM[198]);

    $finish;
  end

  initial begin
    $dumpfile("mips3.vcd");
    $dumpvars(0, mips_tb3);
    $monitor("R2: %0d", mips.REG[2]);
  end

endmodule

outputs/mips3.vcd
$date
	Tue Jun 09 17:54:02 2026
$end
$version
	Icarus Verilog
$end
$timescale
	1s
$end
$scope module mips_tb3 $end
$var reg 1 ! clk1 $end
$var reg 1 " clk2 $end
$var integer 32 # k [31:0] $end
$scope module mips $end
$var wire 1 ! clk1 $end
$var wire 1 " clk2 $end
$var parameter 6 $ ADD $end
$var parameter 6 % ADDI $end
$var parameter 6 & AND $end
$var parameter 6 ' BEQZ $end
$var parameter 6 ( BNEQZ $end
$var parameter 3 ) BRANCH $end
$var parameter 3 * HALT $end
$var parameter 6 + HLT $end
$var parameter 3 , LOAD $end
$var parameter 6 - LW $end
$var parameter 6 . MUL $end
$var parameter 6 / OR $end
$var parameter 3 0 RM_ALU $end
$var parameter 3 1 RR_ALU $end
$var parameter 6 2 SLT $end
$var parameter 6 3 SLTI $end
$var parameter 3 4 STORE $end
$var parameter 6 5 SUB $end
$var parameter 6 6 SUBI $end
$var parameter 6 7 SW $end
$var reg 32 8 EX_MEM_ALUOUT [31:0] $end
$var reg 32 9 EX_MEM_B [31:0] $end
$var reg 1 : EX_MEM_COND $end
$var reg 32 ; EX_MEM_IR [31:0] $end
$var reg 3 < EX_MEM_TYPE [2:0] $end
$var reg 1 = HALTED $end
$var reg 32 > ID_EX_A [31:0] $end
$var reg 32 ? ID_EX_B [31:0] $end
$var reg 32 @ ID_EX_IMM [31:0] $end
$var reg 32 A ID_EX_IR [31:0] $end
$var reg 32 B ID_EX_NPC [31:0] $end
$var reg 3 C ID_EX_TYPE [2:0] $end
$var reg 32 D IF_ID_IR [31:0] $end
$var reg 32 E IF_ID_NPC [31:0] $end
$var reg 32 F MEM_WB_ALUOUT [31:0] $end
$var reg 32 G MEM_WB_IR [31:0] $end
$var reg 32 H MEM_WB_LMD [31:0] $end
$var reg 3 I MEM_WB_TYPE [2:0] $end
$var reg 32 J PC [31:0] $end
$var reg 1 K TAKEN_BRANCH $end
$upscope $end
$upscope $end
$enddefinitions $end
$comment Show the parameter values. $end
$dumpall
b1001 7
b1011 6
b1 5
b11 4
b1100 3
b100 2
b0 1
b1 0
b11 /
b101 .
b1000 -
b10 ,
b111111 +
b101 *
b100 )
b1101 (
b1110 '
b10 &
b1010 %
b0 $
$end
#0
$dumpvars
0K
b0 J
bx I
bx H
bx G
bx F
bx E
bx D
bx C
bx B
bx A
bx @
bx ?
bx >
0=
bx <
bx ;
x:
bx 9
bx 8
b11111 #
0"
0!
$end
#5
1!
#7
b1 J
b1 E
b101000000010100000000011001000 D
#10
0!
#15
b0 >
1"
#17
b1 C
b1010 ?
b11001000 @
b101000000010100000000011001000 A
b1 B
#20
0"
#25
1!
#27
b11001000 8
b1 <
b101000000010100000000011001000 ;
b10 J
b10 E
b101000000000100000000000000001 D
#30
0!
#35
b1 I
b101000000010100000000011001000 G
1"
#37
b11001000 F
b10 ?
b1 @
b101000000000100000000000000001 A
b10 B
#40
0"
#45
1!
#47
b11 J
b11 E
b100001010000110000000000000000 D
b1 8
b101000000000100000000000000001 ;
#50
0!
#55
b101000000000100000000000000001 G
1"
#57
b10 C
b11 ?
b11001000 >
b0 @
b100001010000110000000000000000 A
b11 B
b1 F
#60
0"
#65
1!
#67
b11 9
b11001000 8
b10 <
b100001010000110000000000000000 ;
b100 J
b100 E
b1110100101001010000000000000 D
#70
0!
#75
b10 I
b100001010000110000000000000000 G
1"
#77
b111 H
b0 C
b10100 ?
b10100 >
b11111111111111111010000000000000 @
b1110100101001010000000000000 A
b100 B
#80
0"
#85
1!
#87
b101 J
b101 E
b10100010000110001000000000000 D
b10100 8
b0 <
b1110100101001010000000000000 ;
#90
0!
#95
b0 I
b1110100101001010000000000000 G
1"
#97
b111 ?
b1 >
b1000000000000 @
b10100010000110001000000000000 A
b101 B
b10100 F
#100
0"
#105
1!
#107
b111 8
b10100010000110001000000000000 ;
b110 J
b110 E
b101100011000110000000000000001 D
#110
0!
#115
b10100010000110001000000000000 G
1"
#117
b111 F
b1 C
b111 >
b1 @
b101100011000110000000000000001 A
b110 B
#120
0"
#125
1!
#127
b111 J
b111 E
b1110100101001010000000000000 D
b110 8
b1 <
b101100011000110000000000000001 ;
#130
0!
#135
b1 I
b101100011000110000000000000001 G
1"
#137
b0 C
b10100 ?
b10100 >
b11111111111111111010000000000000 @
b1110100101001010000000000000 A
b111 B
b110 F
#140
0"
#145
1!
#147
b10100 8
b0 <
b1110100101001010000000000000 ;
b1000 J
b1000 E
b110100011000001111111111111100 D
#150
0!
#155
b0 I
b1110100101001010000000000000 G
b0 ?
1"
#157
b10100 F
b100 C
b110 >
b11111111111111111111111111111100 @
b110100011000001111111111111100 A
b1000 B
#160
0"
#165
1!
#167
b1001 J
b1001 E
b100101010000101111111111111110 D
0:
b100 8
b100 <
b110100011000001111111111111100 ;
#170
0!
#175
b100 I
b110100011000001111111111111100 G
1"
#177
b11 C
b111 ?
b11001000 >
b11111111111111111111111111111110 @
b100101010000101111111111111110 A
b1001 B
#180
0"
#185
1!
#187
b111 9
b11000110 8
b11 <
b100101010000101111111111111110 ;
b101 J
b101 E
0K
b10100010000110001000000000000 D
#190
0!
#195
b11 I
b100101010000101111111111111110 G
1"
#197
b0 C
b110 ?
b111 >
b1000000000000 @
b10100010000110001000000000000 A
b101 B
#200
0"
#205
1!
#207
b110 J
b110 E
b101100011000110000000000000001 D
b101010 8
b0 <
b10100010000110001000000000000 ;
#210
0!
#215
b0 I
b10100010000110001000000000000 G
1"
#217
b1 C
b110 >
b1 @
b101100011000110000000000000001 A
b110 B
b101010 F
#220
0"
#225
1!
#227
b101 8
b1 <
b101100011000110000000000000001 ;
b111 J
b111 E
b1110100101001010000000000000 D
#230
0!
#235
b1 I
b101100011000110000000000000001 G
1"
#237
b101 F
b0 C
b10100 ?
b10100 >
b11111111111111111010000000000000 @
b1110100101001010000000000000 A
b111 B
#240
0"
#245
1!
#247
b1000 J
b1000 E
b110100011000001111111111111100 D
b10100 8
b0 <
b1110100101001010000000000000 ;
#250
0!
#255
b0 ?
b0 I
b1110100101001010000000000000 G
1"
#257
b100 C
b101 >
b11111111111111111111111111111100 @
b110100011000001111111111111100 A
b1000 B
b10100 F
#260
0"
#265
1!
#267
b100 8
b100 <
b110100011000001111111111111100 ;
b1001 J
b1001 E
b100101010000101111111111111110 D
#270
0!
#275
b100 I
b110100011000001111111111111100 G
1"
#277
b11 C
b101010 ?
b11001000 >
b11111111111111111111111111111110 @
b100101010000101111111111111110 A
b1001 B
#280
0"
#285
1!
#287
b101 J
b101 E
1K
b10100010000110001000000000000 D
b101010 9
b11000110 8
b11 <
b100101010000101111111111111110 ;
#290
0!
#295
b11 I
b100101010000101111111111111110 G
1"
#297
b0 C
b101 ?
b101010 >
b1000000000000 @
b10100010000110001000000000000 A
b101 B
#300
0"
#305
1!
#307
b11010010 8
b0 <
b10100010000110001000000000000 ;
0K
b110 J
b110 E
b101100011000110000000000000001 D
#310
0!
#315
b0 I
b10100010000110001000000000000 G
1"
#317
b11010010 F
b1 C
b101 >
b1 @
b101100011000110000000000000001 A
b110 B
#320
0"
#325
1!
#327
b111 J
b111 E
b1110100101001010000000000000 D
b100 8
b1 <
b101100011000110000000000000001 ;
#330
0!
#335
b1 I
b101100011000110000000000000001 G
1"
#337
b0 C
b10100 ?
b10100 >
b11111111111111111010000000000000 @
b1110100101001010000000000000 A
b111 B
b100 F
#340
0"
#345
1!
#347
b10100 8
b0 <
b1110100101001010000000000000 ;
b1000 J
b1000 E
b110100011000001111111111111100 D
#350
0!
#355
b0 I
b1110100101001010000000000000 G
b0 ?
1"
#357
b10100 F
b100 C
b100 >
b11111111111111111111111111111100 @
b110100011000001111111111111100 A
b1000 B
#360
0"
#365
1!
#367
b1001 J
b1001 E
b100101010000101111111111111110 D
b100 8
b100 <
b110100011000001111111111111100 ;
#370
0!
#375
b100 I
b110100011000001111111111111100 G
1"
#377
b11 C
b11010010 ?
b11001000 >
b11111111111111111111111111111110 @
b100101010000101111111111111110 A
b1001 B
#380
0"
#385
1!
#387
b11010010 9
b11000110 8
b11 <
b100101010000101111111111111110 ;
b101 J
b101 E
0K
b10100010000110001000000000000 D
#390
0!
#395
b11 I
b100101010000101111111111111110 G
1"
#397
b0 C
b100 ?
b11010010 >
b1000000000000 @
b10100010000110001000000000000 A
b101 B
#400
0"
#405
1!
#407
b110 J
b110 E
b101100011000110000000000000001 D
b1101001000 8
b0 <
b10100010000110001000000000000 ;
#410
0!
#415
b0 I
b10100010000110001000000000000 G
1"
#417
b1 C
b100 >
b1 @
b101100011000110000000000000001 A
b110 B
b1101001000 F
#420
0"
#425
1!
#427
b11 8
b1 <
b101100011000110000000000000001 ;
b111 J
b111 E
b1110100101001010000000000000 D
#430
0!
#435
b1 I
b101100011000110000000000000001 G
1"
#437
b11 F
b0 C
b10100 ?
b10100 >
b11111111111111111010000000000000 @
b1110100101001010000000000000 A
b111 B
#440
0"
#445
1!
#447
b1000 J
b1000 E
b110100011000001111111111111100 D
b10100 8
b0 <
b1110100101001010000000000000 ;
#450
0!
#455
b0 ?
b0 I
b1110100101001010000000000000 G
1"
#457
b100 C
b11 >
b11111111111111111111111111111100 @
b110100011000001111111111111100 A
b1000 B
b10100 F
#460
0"
#465
1!
#467
b100 8
b100 <
b110100011000001111111111111100 ;
b1001 J
b1001 E
b100101010000101111111111111110 D
#470
0!
#475
b100 I
b110100011000001111111111111100 G
1"
#477
b11 C
b1101001000 ?
b11001000 >
b11111111111111111111111111111110 @
b100101010000101111111111111110 A
b1001 B
#480
0"
#485
1!
#487
b101 J
b101 E
1K
b10100010000110001000000000000 D
b1101001000 9
b11000110 8
b11 <
b100101010000101111111111111110 ;
#490
0!
#495
b11 I
b100101010000101111111111111110 G
1"
#497
b0 C
b11 ?
b1101001000 >
b1000000000000 @
b10100010000110001000000000000 A
b101 B
#500
0"
#505
1!
#507
b100111011000 8
b0 <
b10100010000110001000000000000 ;
0K
b110 J
b110 E
b101100011000110000000000000001 D
#510
0!
#515
b0 I
b10100010000110001000000000000 G
1"
#517
b100111011000 F
b1 C
b11 >
b1 @
b101100011000110000000000000001 A
b110 B
#520
0"
#525
1!
#527
b111 J
b111 E
b1110100101001010000000000000 D
b10 8
b1 <
b101100011000110000000000000001 ;
#530
0!
#535
b1 I
b101100011000110000000000000001 G
1"
#537
b0 C
b10100 ?
b10100 >
b11111111111111111010000000000000 @
b1110100101001010000000000000 A
b111 B
b10 F
#540
0"
#545
1!
#547
b10100 8
b0 <
b1110100101001010000000000000 ;
b1000 J
b1000 E
b110100011000001111111111111100 D
#550
0!
#555
b0 I
b1110100101001010000000000000 G
b0 ?
1"
#557
b10100 F
b100 C
b10 >
b11111111111111111111111111111100 @
b110100011000001111111111111100 A
b1000 B
#560
0"
#565
1!
#567
b1001 J
b1001 E
b100101010000101111111111111110 D
b100 8
b100 <
b110100011000001111111111111100 ;
#570
0!
#575
b100 I
b110100011000001111111111111100 G
1"
#577
b11 C
b100111011000 ?
b11001000 >
b11111111111111111111111111111110 @
b100101010000101111111111111110 A
b1001 B
#580
0"
#585
1!
#587
b100111011000 9
b11000110 8
b11 <
b100101010000101111111111111110 ;
b101 J
b101 E
0K
b10100010000110001000000000000 D
#590
0!
#595
b11 I
b100101010000101111111111111110 G
1"
#597
b0 C
b10 ?
b100111011000 >
b1000000000000 @
b10100010000110001000000000000 A
b101 B
#600
0"
#605
1!
#607
b110 J
b110 E
b101100011000110000000000000001 D
b1001110110000 8
b0 <
b10100010000110001000000000000 ;
#610
0!
#615
b0 I
b10100010000110001000000000000 G
1"
#617
b1 C
b10 >
b1 @
b101100011000110000000000000001 A
b110 B
b1001110110000 F
#620
0"
#625
1!
#627
b1 8
b1 <
b101100011000110000000000000001 ;
b111 J
b111 E
b1110100101001010000000000000 D
#630
0!
#635
b1 I
b101100011000110000000000000001 G
1"
#637
b1 F
b0 C
b10100 ?
b10100 >
b11111111111111111010000000000000 @
b1110100101001010000000000000 A
b111 B
#640
0"
#645
1!
#647
b1000 J
b1000 E
b110100011000001111111111111100 D
b10100 8
b0 <
b1110100101001010000000000000 ;
#650
0!
#655
b0 ?
b0 I
b1110100101001010000000000000 G
1"
#657
b100 C
b1 >
b11111111111111111111111111111100 @
b110100011000001111111111111100 A
b1000 B
b10100 F
#660
0"
#665
1!
#667
b100 8
b100 <
b110100011000001111111111111100 ;
b1001 J
b1001 E
b100101010000101111111111111110 D
#670
0!
#675
b100 I
b110100011000001111111111111100 G
1"
#677
b11 C
b1001110110000 ?
b11001000 >
b11111111111111111111111111111110 @
b100101010000101111111111111110 A
b1001 B
#680
0"
#685
1!
#687
b101 J
b101 E
1K
b10100010000110001000000000000 D
b1001110110000 9
b11000110 8
b11 <
b100101010000101111111111111110 ;
#690
0!
#695
b11 I
b100101010000101111111111111110 G
1"
#697
b0 C
b1 ?
b1001110110000 >
b1000000000000 @
b10100010000110001000000000000 A
b101 B
#700
0"
#705
1!
#707
b1001110110000 8
b0 <
b10100010000110001000000000000 ;
0K
b110 J
b110 E
b101100011000110000000000000001 D
#710
0!
#715
b0 I
b10100010000110001000000000000 G
1"
#717
b1001110110000 F
b1 C
b1 >
b1 @
b101100011000110000000000000001 A
b110 B
#720
0"
#725
1!
#727
b111 J
b111 E
b1110100101001010000000000000 D
b0 8
b1 <
b101100011000110000000000000001 ;
#730
0!
#735
b1 I
b101100011000110000000000000001 G
1"
#737
b0 C
b10100 ?
b10100 >
b11111111111111111010000000000000 @
b1110100101001010000000000000 A
b111 B
b0 F
#740
0"
#745
1!
#747
b10100 8
b0 <
b1110100101001010000000000000 ;
b1000 J
b1000 E
b110100011000001111111111111100 D
#750
0!
#755
b0 I
b1110100101001010000000000000 G
b0 ?
1"
#757
b10100 F
b100 C
b0 >
b11111111111111111111111111111100 @
b110100011000001111111111111100 A
b1000 B
#760
0"
#765
1!
#767
b1001 J
b1001 E
b100101010000101111111111111110 D
1:
b100 8
b100 <
b110100011000001111111111111100 ;
#770
0!
#775
b100 I
b110100011000001111111111111100 G
1"
#777
b11 C
b1001110110000 ?
b11001000 >
b11111111111111111111111111111110 @
b100101010000101111111111111110 A
b1001 B
#780
0"
#785
1!
#787
b11000110 8
b11 <
b100101010000101111111111111110 ;
b1010 J
b1010 E
b11111100000000000000000000000000 D
#790
0!
#795
b11 I
b100101010000101111111111111110 G
b0 ?
b0 >
1"
#797
b101 C
b0 @
b11111100000000000000000000000000 A
b1010 B
#800
0"
#805
1!
#807
b1011 J
b1011 E
bx D
b101 <
b11111100000000000000000000000000 ;
#810
0!
#815
b101 I
b11111100000000000000000000000000 G
1"
#817
bx ?
bx >
bx @
bx A
b1011 B
#820
0"
#825
1!
#827
1=
bx ;
b1100 J
b1100 E
